{"2009-2010": [{"Portsmouth": {"dg": -32, "pt": 28}}, {"Hull City": {"dg": -41, "pt": 30}}, {"Burnley": {"dg": -40, "pt": 30}}, {"West Ham United": {"dg": -19, "pt": 35}}, {"Wigan Athletic": {"dg": -42, "pt": 36}}, {"Wolverhampton": {"dg": -24, "pt": 38}}, {"Bolton Wanderers": {"dg": -25, "pt": 39}}, {"Sunderland": {"dg": -8, "pt": 44}}, {"Fulham": {"dg": -7, "pt": 46}}, {"Stoke City": {"dg": -14, "pt": 47}}, {"Blackburn Rovers": {"dg": -14, "pt": 50}}, {"Birmingham": {"dg": -9, "pt": 50}}, {"Everton": {"dg": 11, "pt": 61}}, {"Liverpool": {"dg": 26, "pt": 63}}, {"Aston Villa": {"dg": 13, "pt": 64}}, {"Manchester City": {"dg": 28, "pt": 67}}, {"Tottenham Hotspur": {"dg": 26, "pt": 70}}, {"Arsenal": {"dg": 42, "pt": 75}}, {"Manchester United": {"dg": 58, "pt": 85}}, {"Chelsea": {"dg": 71, "pt": 86}}], "2002-2003": [{"Sunderland": {"dg": -44, "pt": 19}}, {"West Bromwich Albion": {"dg": -36, "pt": 26}}, {"West Ham United": {"dg": -17, "pt": 42}}, {"Bolton Wanderers": {"dg": -10, "pt": 44}}, {"Aston Villa": {"dg": -5, "pt": 45}}, {"Leeds United": {"dg": 1, "pt": 47}}, {"Fulham": {"dg": -9, "pt": 48}}, {"Birmingham": {"dg": -8, "pt": 48}}, {"Charlton Athletic": {"dg": -11, "pt": 49}}, {"Middlesboro": {"dg": 4, "pt": 49}}, {"Tottenham Hotspur": {"dg": -11, "pt": 50}}, {"Manchester City": {"dg": -7, "pt": 51}}, {"Southampton": {"dg": -3, "pt": 52}}, {"Everton": {"dg": -1, "pt": 59}}, {"Blackburn Rovers": {"dg": 9, "pt": 60}}, {"Liverpool": {"dg": 20, "pt": 64}}, {"Chelsea": {"dg": 30, "pt": 67}}, {"Newcastle United": {"dg": 15, "pt": 69}}, {"Arsenal": {"dg": 43, "pt": 78}}, {"Manchester United": {"dg": 40, "pt": 83}}], "2005-2006": [{"Sunderland": {"dg": -43, "pt": 15}}, {"West Bromwich Albion": {"dg": -27, "pt": 30}}, {"Birmingham": {"dg": -22, "pt": 34}}, {"Portsmouth": {"dg": -25, "pt": 38}}, {"Aston Villa": {"dg": -13, "pt": 42}}, {"Manchester City": {"dg": -5, "pt": 43}}, {"Middlesboro": {"dg": -10, "pt": 45}}, {"Charlton Athletic": {"dg": -14, "pt": 47}}, {"Fulham": {"dg": -10, "pt": 48}}, {"Everton": {"dg": -15, "pt": 50}}, {"Wigan Athletic": {"dg": -7, "pt": 51}}, {"West Ham United": {"dg": -3, "pt": 55}}, {"Bolton Wanderers": {"dg": 8, "pt": 56}}, {"Newcastle United": {"dg": 5, "pt": 58}}, {"Blackburn Rovers": {"dg": 9, "pt": 63}}, {"Tottenham Hotspur": {"dg": 15, "pt": 65}}, {"Arsenal": {"dg": 37, "pt": 67}}, {"Liverpool": {"dg": 32, "pt": 82}}, {"Manchester United": {"dg": 38, "pt": 83}}, {"Chelsea": {"dg": 50, "pt": 91}}], "2007-2008": [{"Derby County": {"dg": -69, "pt": 11}}, {"Birmingham": {"dg": -16, "pt": 35}}, {"Reading": {"dg": -25, "pt": 36}}, {"Fulham": {"dg": -22, "pt": 36}}, {"Bolton Wanderers": {"dg": -18, "pt": 37}}, {"Sunderland": {"dg": -23, "pt": 39}}, {"Wigan Athletic": {"dg": -17, "pt": 40}}, {"Middlesboro": {"dg": -10, "pt": 42}}, {"Newcastle United": {"dg": -20, "pt": 43}}, {"Tottenham Hotspur": {"dg": 5, "pt": 46}}, {"West Ham United": {"dg": -8, "pt": 49}}, {"Manchester City": {"dg": -8, "pt": 55}}, {"Portsmouth": {"dg": 8, "pt": 57}}, {"Blackburn Rovers": {"dg": 2, "pt": 58}}, {"Aston Villa": {"dg": 20, "pt": 60}}, {"Everton": {"dg": 22, "pt": 65}}, {"Liverpool": {"dg": 39, "pt": 76}}, {"Arsenal": {"dg": 43, "pt": 83}}, {"Chelsea": {"dg": 39, "pt": 85}}, {"Manchester United": {"dg": 58, "pt": 87}}], "2004-2005": [{"Southampton": {"dg": -21, "pt": 32}}, {"Norwich City": {"dg": -35, "pt": 33}}, {"Crystal Palace": {"dg": -21, "pt": 33}}, {"West Bromwich Albion": {"dg": -25, "pt": 34}}, {"Portsmouth": {"dg": -16, "pt": 39}}, {"Blackburn Rovers": {"dg": -11, "pt": 42}}, {"Newcastle United": {"dg": -10, "pt": 44}}, {"Fulham": {"dg": -8, "pt": 44}}, {"Birmingham": {"dg": -6, "pt": 45}}, {"Charlton Athletic": {"dg": -16, "pt": 46}}, {"Aston Villa": {"dg": -7, "pt": 47}}, {"Tottenham Hotspur": {"dg": 6, "pt": 52}}, {"Manchester City": {"dg": 8, "pt": 52}}, {"Middlesboro": {"dg": 7, "pt": 55}}, {"Bolton Wanderers": {"dg": 5, "pt": 58}}, {"Liverpool": {"dg": 11, "pt": 58}}, {"Everton": {"dg": -1, "pt": 61}}, {"Manchester United": {"dg": 32, "pt": 77}}, {"Arsenal": {"dg": 51, "pt": 83}}, {"Chelsea": {"dg": 57, "pt": 95}}], "2003-2004": [{"Wolverhampton": {"dg": -39, "pt": 33}}, {"Leeds United": {"dg": -39, "pt": 33}}, {"Leicester City": {"dg": -17, "pt": 33}}, {"Everton": {"dg": -12, "pt": 39}}, {"Manchester City": {"dg": 1, "pt": 41}}, {"Blackburn Rovers": {"dg": -8, "pt": 44}}, {"Tottenham Hotspur": {"dg": -10, "pt": 45}}, {"Portsmouth": {"dg": -7, "pt": 45}}, {"Southampton": {"dg": -1, "pt": 47}}, {"Middlesboro": {"dg": -8, "pt": 48}}, {"Birmingham": {"dg": -5, "pt": 50}}, {"Fulham": {"dg": 6, "pt": 52}}, {"Bolton Wanderers": {"dg": -8, "pt": 53}}, {"Charlton Athletic": {"dg": 0, "pt": 53}}, {"Aston Villa": {"dg": 4, "pt": 56}}, {"Newcastle United": {"dg": 12, "pt": 56}}, {"Liverpool": {"dg": 18, "pt": 60}}, {"Manchester United": {"dg": 29, "pt": 75}}, {"Chelsea": {"dg": 37, "pt": 79}}, {"Arsenal": {"dg": 47, "pt": 90}}], "2001-2002": [{"Leicester City": {"dg": -34, "pt": 28}}, {"Derby County": {"dg": -29, "pt": 30}}, {"Ipswich Town": {"dg": -23, "pt": 36}}, {"Sunderland": {"dg": -22, "pt": 40}}, {"Bolton Wanderers": {"dg": -18, "pt": 40}}, {"Everton": {"dg": -12, "pt": 43}}, {"Charlton Athletic": {"dg": -11, "pt": 44}}, {"Fulham": {"dg": -8, "pt": 44}}, {"Middlesboro": {"dg": -12, "pt": 45}}, {"Southampton": {"dg": -8, "pt": 45}}, {"Blackburn Rovers": {"dg": 3, "pt": 46}}, {"Tottenham Hotspur": {"dg": -4, "pt": 50}}, {"Aston Villa": {"dg": -1, "pt": 50}}, {"West Ham United": {"dg": -9, "pt": 53}}, {"Chelsea": {"dg": 28, "pt": 64}}, {"Leeds United": {"dg": 16, "pt": 66}}, {"Newcastle United": {"dg": 22, "pt": 71}}, {"Manchester United": {"dg": 42, "pt": 77}}, {"Liverpool": {"dg": 37, "pt": 80}}, {"Arsenal": {"dg": 43, "pt": 87}}], "2011-2012": [{"Wolverhampton": {"dg": -42, "pt": 25}}, {"Blackburn Rovers": {"dg": -30, "pt": 31}}, {"Bolton Wanderers": {"dg": -31, "pt": 36}}, {"Queens Park Rangers": {"dg": -23, "pt": 37}}, {"Aston Villa": {"dg": -16, "pt": 38}}, {"Wigan Athletic": {"dg": -20, "pt": 43}}, {"Stoke City": {"dg": -17, "pt": 45}}, {"Sunderland": {"dg": -1, "pt": 45}}, {"Norwich City": {"dg": -14, "pt": 47}}, {"Swansea City": {"dg": -7, "pt": 47}}, {"West Bromwich Albion": {"dg": -7, "pt": 47}}, {"Fulham": {"dg": -3, "pt": 52}}, {"Liverpool": {"dg": 7, "pt": 52}}, {"Everton": {"dg": 10, "pt": 56}}, {"Chelsea": {"dg": 19, "pt": 64}}, {"Newcastle United": {"dg": 5, "pt": 65}}, {"Tottenham Hotspur": {"dg": 25, "pt": 69}}, {"Arsenal": {"dg": 25, "pt": 70}}, {"Manchester United": {"dg": 56, "pt": 89}}, {"Manchester City": {"dg": 64, "pt": 89}}], "2006-2007": [{"Watford": {"dg": -30, "pt": 28}}, {"Charlton Athletic": {"dg": -26, "pt": 34}}, {"Sheffield United": {"dg": -23, "pt": 38}}, {"Wigan Athletic": {"dg": -22, "pt": 38}}, {"Fulham": {"dg": -22, "pt": 39}}, {"West Ham United": {"dg": -24, "pt": 41}}, {"Manchester City": {"dg": -15, "pt": 42}}, {"Newcastle United": {"dg": -9, "pt": 43}}, {"Middlesboro": {"dg": -5, "pt": 46}}, {"Aston Villa": {"dg": 2, "pt": 50}}, {"Blackburn Rovers": {"dg": -2, "pt": 52}}, {"Portsmouth": {"dg": 3, "pt": 54}}, {"Reading": {"dg": 5, "pt": 55}}, {"Bolton Wanderers": {"dg": -5, "pt": 56}}, {"Everton": {"dg": 16, "pt": 58}}, {"Tottenham Hotspur": {"dg": 3, "pt": 60}}, {"Arsenal": {"dg": 28, "pt": 68}}, {"Liverpool": {"dg": 30, "pt": 68}}, {"Chelsea": {"dg": 40, "pt": 83}}, {"Manchester United": {"dg": 56, "pt": 89}}], "2010-2011": [{"West Ham United": {"dg": -27, "pt": 33}}, {"Blackpool": {"dg": -23, "pt": 39}}, {"Birmingham": {"dg": -21, "pt": 39}}, {"Wolverhampton": {"dg": -20, "pt": 40}}, {"Wigan Athletic": {"dg": -21, "pt": 42}}, {"Blackburn Rovers": {"dg": -13, "pt": 43}}, {"Bolton Wanderers": {"dg": -4, "pt": 46}}, {"Stoke City": {"dg": -2, "pt": 46}}, {"Newcastle United": {"dg": -1, "pt": 46}}, {"West Bromwich Albion": {"dg": -15, "pt": 47}}, {"Sunderland": {"dg": -11, "pt": 47}}, {"Aston Villa": {"dg": -11, "pt": 48}}, {"Fulham": {"dg": 6, "pt": 49}}, {"Everton": {"dg": 6, "pt": 54}}, {"Liverpool": {"dg": 15, "pt": 58}}, {"Tottenham Hotspur": {"dg": 9, "pt": 62}}, {"Arsenal": {"dg": 29, "pt": 68}}, {"Manchester City": {"dg": 27, "pt": 71}}, {"Chelsea": {"dg": 36, "pt": 71}}, {"Manchester United": {"dg": 41, "pt": 80}}], "2008-2009": [{"West Bromwich Albion": {"dg": -31, "pt": 32}}, {"Middlesboro": {"dg": -29, "pt": 32}}, {"Newcastle United": {"dg": -19, "pt": 34}}, {"Hull City": {"dg": -25, "pt": 35}}, {"Sunderland": {"dg": -20, "pt": 36}}, {"Blackburn Rovers": {"dg": -20, "pt": 41}}, {"Portsmouth": {"dg": -19, "pt": 41}}, {"Bolton Wanderers": {"dg": -12, "pt": 41}}, {"Stoke City": {"dg": -17, "pt": 45}}, {"Wigan Athletic": {"dg": -11, "pt": 45}}, {"Manchester City": {"dg": 8, "pt": 50}}, {"West Ham United": {"dg": -3, "pt": 51}}, {"Tottenham Hotspur": {"dg": 0, "pt": 51}}, {"Fulham": {"dg": 5, "pt": 53}}, {"Aston Villa": {"dg": 6, "pt": 62}}, {"Everton": {"dg": 18, "pt": 63}}, {"Arsenal": {"dg": 31, "pt": 72}}, {"Chelsea": {"dg": 44, "pt": 83}}, {"Liverpool": {"dg": 50, "pt": 86}}, {"Manchester United": {"dg": 44, "pt": 90}}], "2012-2013": [{"Queens Park Rangers": {"dg": -30, "pt": 25}}, {"Reading": {"dg": -30, "pt": 28}}, {"Wigan Athletic": {"dg": -26, "pt": 36}}, {"Sunderland": {"dg": -13, "pt": 39}}, {"Newcastle United": {"dg": -23, "pt": 41}}, {"Aston Villa": {"dg": -22, "pt": 41}}, {"Southampton": {"dg": -11, "pt": 41}}, {"Stoke City": {"dg": -11, "pt": 42}}, {"Fulham": {"dg": -10, "pt": 43}}, {"Norwich City": {"dg": -17, "pt": 44}}, {"West Ham United": {"dg": -8, "pt": 46}}, {"Swansea City": {"dg": -4, "pt": 46}}, {"West Bromwich Albion": {"dg": -4, "pt": 49}}, {"Liverpool": {"dg": 28, "pt": 61}}, {"Everton": {"dg": 15, "pt": 63}}, {"Tottenham Hotspur": {"dg": 20, "pt": 72}}, {"Arsenal": {"dg": 35, "pt": 73}}, {"Chelsea": {"dg": 36, "pt": 75}}, {"Manchester City": {"dg": 32, "pt": 78}}, {"Manchester United": {"dg": 43, "pt": 89}}]}